{
 "actions": [],
 "allow_rename": 1,
 "creation": "2023-06-06 11:14:02.805699",
 "doctype": "DocType",
 "editable_grid": 1,
 "engine": "InnoDB",
 "field_order": [
  "jmi_uom"
 ],
 "fields": [
  {
   "fieldname": "jmi_uom",
   "fieldtype": "Link",
   "in_list_view": 1,
   "label": "JMI UOM",
   "options": "JMI UOM",
   "reqd": 1
  }
 ],
 "index_web_pages_for_search": 1,
 "istable": 1,
 "links": [],
 "modified": "2023-06-06 11:14:02.805699",
 "modified_by": "Administrator",
 "module": "jute_mark_india",
 "name": "Product Type UOM",
 "owner": "Administrator",
 "permissions": [],
 "sort_field": "modified",
 "sort_order": "DESC",
 "states": []
}